<?xml version="1.0" encoding="utf-8"?>
<Research Direction="高分软件大赛" ImageName="1.tif">
   <Department>参赛单位</Department>
   <Date>2017-7-10</Date>
   <PluginName>目标识别</PluginName>
   <PluginClass>检测</PluginClass>
   <Results Coordinate="Pixel">
      <Object>tank</Object>
      <tank_name tank_name="2"/>
      <Pixel Coordinate="X and Y">
         <Pt Index="1" LeftTopX="589" LeftTopY="296" RightBottomX="" RightBottomY=""/>
         <Pt Index="2" LeftTopX="716" LeftTopY="296" RightBottomX="" RightBottomY=""/>
         <Pt Index="3" LeftTopX="716" LeftTopY="423" RightBottomX="" RightBottomY=""/>
         <Pt Index="4" LeftTopX="589" LeftTopY="423" RightBottomX="" RightBottomY=""/>
      </Pixel>
      <Object>tank</Object>
      <tank_name tank_name="2"/>
      <Pixel Coordinate="X and Y">
         <Pt Index="1" LeftTopX="854" LeftTopY="440" RightBottomX="" RightBottomY=""/>
         <Pt Index="2" LeftTopX="981" LeftTopY="440" RightBottomX="" RightBottomY=""/>
         <Pt Index="3" LeftTopX="981" LeftTopY="567" RightBottomX="" RightBottomY=""/>
         <Pt Index="4" LeftTopX="854" LeftTopY="567" RightBottomX="" RightBottomY=""/>
      </Pixel>
      <Object>tank</Object>
      <tank_name tank_name="3"/>
      <Pixel Coordinate="X and Y">
         <Pt Index="1" LeftTopX="453" LeftTopY="1451" RightBottomX="" RightBottomY=""/>
         <Pt Index="2" LeftTopX="580" LeftTopY="1451" RightBottomX="" RightBottomY=""/>
         <Pt Index="3" LeftTopX="580" LeftTopY="1578" RightBottomX="" RightBottomY=""/>
         <Pt Index="4" LeftTopX="453" LeftTopY="1578" RightBottomX="" RightBottomY=""/>
      </Pixel>
      <Object>tank</Object>
      <tank_name tank_name="3"/>
      <Pixel Coordinate="X and Y">
         <Pt Index="1" LeftTopX="678" LeftTopY="1013" RightBottomX="" RightBottomY=""/>
         <Pt Index="2" LeftTopX="805" LeftTopY="1013" RightBottomX="" RightBottomY=""/>
         <Pt Index="3" LeftTopX="805" LeftTopY="1140" RightBottomX="" RightBottomY=""/>
         <Pt Index="4" LeftTopX="678" LeftTopY="1140" RightBottomX="" RightBottomY=""/>
      </Pixel>
   </Results>
</Research>