<?xml version="1.0" encoding="utf-8"?>
<Research Direction="高分软件大赛" ImageName="1.tif">
   <Department>参赛单位</Department>
   <Date>2017-7-10</Date>
   <PluginName>目标识别</PluginName>
   <PluginClass>检测</PluginClass>
   <Results Coordinate="Pixel">
      <Object>tank</Object>
      <tank_name tank_name="3"/>
      <Pixel Coordinate="X and Y">
         <Pt Index="1" LeftTopX="104" LeftTopY="1094" RightBottomX="" RightBottomY=""/>
         <Pt Index="2" LeftTopX="231" LeftTopY="1094" RightBottomX="" RightBottomY=""/>
         <Pt Index="3" LeftTopX="231" LeftTopY="1221" RightBottomX="" RightBottomY=""/>
         <Pt Index="4" LeftTopX="104" LeftTopY="1221" RightBottomX="" RightBottomY=""/>
      </Pixel>
      <Object>tank</Object>
      <tank_name tank_name="1"/>
      <Pixel Coordinate="X and Y">
         <Pt Index="1" LeftTopX="846" LeftTopY="178" RightBottomX="" RightBottomY=""/>
         <Pt Index="2" LeftTopX="973" LeftTopY="178" RightBottomX="" RightBottomY=""/>
         <Pt Index="3" LeftTopX="973" LeftTopY="305" RightBottomX="" RightBottomY=""/>
         <Pt Index="4" LeftTopX="846" LeftTopY="305" RightBottomX="" RightBottomY=""/>
      </Pixel>
      <Object>tank</Object>
      <tank_name tank_name="2"/>
      <Pixel Coordinate="X and Y">
         <Pt Index="1" LeftTopX="299" LeftTopY="792" RightBottomX="" RightBottomY=""/>
         <Pt Index="2" LeftTopX="426" LeftTopY="792" RightBottomX="" RightBottomY=""/>
         <Pt Index="3" LeftTopX="426" LeftTopY="919" RightBottomX="" RightBottomY=""/>
         <Pt Index="4" LeftTopX="299" LeftTopY="919" RightBottomX="" RightBottomY=""/>
      </Pixel>
      <Object>tank</Object>
      <tank_name tank_name="2"/>
      <Pixel Coordinate="X and Y">
         <Pt Index="1" LeftTopX="1303" LeftTopY="335" RightBottomX="" RightBottomY=""/>
         <Pt Index="2" LeftTopX="1430" LeftTopY="335" RightBottomX="" RightBottomY=""/>
         <Pt Index="3" LeftTopX="1430" LeftTopY="462" RightBottomX="" RightBottomY=""/>
         <Pt Index="4" LeftTopX="1303" LeftTopY="462" RightBottomX="" RightBottomY=""/>
      </Pixel>
      <Object>tank</Object>
      <tank_name tank_name="3"/>
      <Pixel Coordinate="X and Y">
         <Pt Index="1" LeftTopX="172" LeftTopY="1296" RightBottomX="" RightBottomY=""/>
         <Pt Index="2" LeftTopX="299" LeftTopY="1296" RightBottomX="" RightBottomY=""/>
         <Pt Index="3" LeftTopX="299" LeftTopY="1423" RightBottomX="" RightBottomY=""/>
         <Pt Index="4" LeftTopX="172" LeftTopY="1423" RightBottomX="" RightBottomY=""/>
      </Pixel>
      <Object>tank</Object>
      <tank_name tank_name="3"/>
      <Pixel Coordinate="X and Y">
         <Pt Index="1" LeftTopX="439" LeftTopY="622" RightBottomX="" RightBottomY=""/>
         <Pt Index="2" LeftTopX="566" LeftTopY="622" RightBottomX="" RightBottomY=""/>
         <Pt Index="3" LeftTopX="566" LeftTopY="749" RightBottomX="" RightBottomY=""/>
         <Pt Index="4" LeftTopX="439" LeftTopY="749" RightBottomX="" RightBottomY=""/>
      </Pixel>
   </Results>
</Research>